setup.py
PBIAT_SELENIUM/PbiATT.py
PBIAT_SELENIUM/__init__.py
PBIAT_SELENIUM.egg-info/PKG-INFO
PBIAT_SELENIUM.egg-info/SOURCES.txt
PBIAT_SELENIUM.egg-info/dependency_links.txt
PBIAT_SELENIUM.egg-info/top_level.txt