Metadata-Version: 2.1
Name: PBIAT-SELENIUM
Version: 1.1
Summary: Pacote para automatizar rotinas PowerBi
Author: Andre Ailton
Author-email: andre.ailtonf.10@gmail.com
Keywords: Selenium,PowerBi,Automatization,automation
